{
  "credit": "Made with Blockbench",
  "parent": "builtin/entity",
  "texture_size": [128, 128],
  "textures": {
    "0": "playdate:block/lollipop_clown_toy",
    "particle": "playdate:block/lollipop_clown_toy"
  },
  "display": {
    "thirdperson_righthand": {
      "rotation": [
        50,
        0,
        0
      ],
      "scale": [
        0.3,
        0.3,
        0.3
      ]
    },
    "thirdperson_lefthand": {
      "rotation": [
        50,
        0,
        0
      ],
      "scale": [
        0.3,
        0.3,
        0.3
      ]
    },
    "firstperson_righthand": {
      "translation": [
        0,
        -4,
        0
      ],
      "scale": [
        0.3,
        0.3,
        0.3
      ]
    },
    "firstperson_lefthand": {
      "translation": [
        0,
        -4,
        0
      ],
      "scale": [
        0.3,
        0.3,
        0.3
      ]
    },
    "ground": {
      "translation": [
        0,
        -1.75,
        0
      ],
      "scale": [
        0.3,
        0.3,
        0.3
      ]
    },
    "gui": {
      "rotation": [
        19,
        -140,
        0
      ],
      "translation": [
        0,
        -6.75,
        0
      ],
      "scale": [
        0.3,
        0.3,
        0.3
      ]
    },
    "head": {
      "translation": [
        0,
        6.5,
        0
      ]
    },
    "fixed": {
      "translation": [
        0,
        -6.75,
        -2.25
      ],
      "scale": [
        0.3,
        0.3,
        0.3
      ]
    }
  }
}